BERTVector/BERTVector.py
BERTVector/__init__.py
BERTVector/test/__init__.py
BERTVector/test/bertvector_test.py
BERTVector/test/test.pkl
BERTVector/test/test.txt
BERTVector-0.3.7.dist-info/LICENSE.txt
BERTVector-0.3.7.dist-info/METADATA
BERTVector-0.3.7.dist-info/WHEEL
BERTVector-0.3.7.dist-info/entry_points.txt
BERTVector-0.3.7.dist-info/top_level.txt
BERTVector-0.3.7.dist-info/RECORD
