Metadata-Version: 2.1
Name: BERTVector
Version: 0.3.7
Summary: extract vector from BERT pre-train model
Home-page: https://github.com/xmxoxo/BERT-Vector
Author: He xi
Author-email: xmhexi@qq.com
License: UNKNOWN
Project-URL: Blog, https://blog.csdn.net/xmxoxo
Keywords: BERT vector extraction tool
Platform: UNKNOWN
Classifier: Development Status :: 5 - Production/Stable
Classifier: Intended Audience :: Developers
Classifier: Topic :: Software Development :: Code Generators
Classifier: License :: OSI Approved :: MIT License
Classifier: Programming Language :: Python :: 3
Classifier: Programming Language :: Python :: 3.4
Classifier: Programming Language :: Python :: 3.5
Classifier: Programming Language :: Python :: 3.6
Requires-Dist: tensorflow (>=1.12.0)
Requires-Dist: numpy (>=1.15.4)
